ciecplib/__init__.py
ciecplib/conftest.py
ciecplib/cookies.py
ciecplib/env.py
ciecplib/kerberos.py
ciecplib/logging.py
ciecplib/requests.py
ciecplib/sessions.py
ciecplib/ui.py
ciecplib/utils.py
ciecplib/x509.py
ciecplib/tests/__init__.py
ciecplib/tests/test_cookies.py
ciecplib/tests/test_env.py
ciecplib/tests/test_kerberos.py
ciecplib/tests/test_requests.py
ciecplib/tests/test_sessions.py
ciecplib/tests/test_utils.py
ciecplib/tests/test_x509.py
ciecplib/tool/__init__.py
ciecplib/tool/ecp_cert_info.py
ciecplib/tool/ecp_curl.py
ciecplib/tool/ecp_get_cert.py
ciecplib/tool/ecp_get_cookie.py
ciecplib/tool/utils.py
ciecplib/tool/tests/__init__.py
ciecplib/tool/tests/test_common.py
ciecplib/tool/tests/test_ecp_cert_info.py
ciecplib/tool/tests/test_ecp_curl.py
ciecplib/tool/tests/test_ecp_get_cert.py
ciecplib/tool/tests/test_utils.py
ciecplib-0.9.0.dist-info/LICENSE
ciecplib-0.9.0.dist-info/METADATA
ciecplib-0.9.0.dist-info/WHEEL
ciecplib-0.9.0.dist-info/entry_points.txt
ciecplib-0.9.0.dist-info/top_level.txt
ciecplib-0.9.0.dist-info/RECORD
