Metadata-Version: 2.2
Name: ciecplib
Version: 0.9.0
Summary: A python client for SAML/ECP authentication
Author-email: Duncan Macleod <duncan.macleod@ligo.org>
License: GPL-3.0-or-later
Project-URL: Bug Tracker, https://github.com/duncanmmacleod/ciecplib/issues
Project-URL: Documentation, https://ciecplib.readthedocs.io/
Project-URL: Source Code, https://github.com/duncanmmacleod/ciecplib/
Classifier: Development Status :: 4 - Beta
Classifier: Intended Audience :: Science/Research
Classifier: License :: OSI Approved :: GNU General Public License v3 or later (GPLv3+)
Classifier: Natural Language :: English
Classifier: Operating System :: OS Independent
Classifier: Programming Language :: Python :: 3
Classifier: Programming Language :: Python :: 3.6
Classifier: Programming Language :: Python :: 3.7
Classifier: Programming Language :: Python :: 3.8
Classifier: Programming Language :: Python :: 3.9
Classifier: Programming Language :: Python :: 3.10
Classifier: Programming Language :: Python :: 3.11
Classifier: Programming Language :: Python :: 3.12
Classifier: Topic :: Scientific/Engineering
Requires-Python: >=3.6
License-File: LICENSE
Requires-Dist: cryptography>=36.0.0
Requires-Dist: requests
Requires-Dist: requests-ecp
Provides-Extra: docs
Requires-Dist: furo; extra == "docs"
Requires-Dist: Sphinx; extra == "docs"
Requires-Dist: sphinx-argparse; extra == "docs"
Requires-Dist: sphinx-automodapi; extra == "docs"
Requires-Dist: sphinx-copybutton; extra == "docs"
Requires-Dist: sphinx-design; extra == "docs"
Requires-Dist: sphinx-github-style; extra == "docs"
Provides-Extra: kerberos
Requires-Dist: gssapi; extra == "kerberos"
Requires-Dist: requests-ecp[kerberos]; extra == "kerberos"
Provides-Extra: manpages
Requires-Dist: argparse-manpage; extra == "manpages"
Provides-Extra: tests
Requires-Dist: pytest>=3.9.0; extra == "tests"
Requires-Dist: pytest-cov; extra == "tests"
Requires-Dist: requests-mock; extra == "tests"
